MANIFEST.in
README.md
README.rst
requirements.txt
setup.py
Crwy.egg-info/PKG-INFO
Crwy.egg-info/SOURCES.txt
Crwy.egg-info/dependency_links.txt
Crwy.egg-info/entry_points.txt
Crwy.egg-info/not-zip-safe
Crwy.egg-info/requires.txt
Crwy.egg-info/top_level.txt
crwy/__init__.py
crwy/changetmpl.py
crwy/cmdline.py
crwy/decorates.py
crwy/exceptions.py
crwy/spider.py
crwy/settings/__init__.py
crwy/settings/default_settings.py
crwy/templates/project/logger_py2.conf.tmpl
crwy/templates/project/logger_py3.conf.tmpl
crwy/templates/spiders/crwybasic.tmpl
crwy/templates/spiders/crwycrawl.tmpl
crwy/templates/spiders/crwyredis.tmpl
crwy/utils/__init__.py
crwy/utils/common.py
crwy/utils/load_settings.py
crwy/utils/logger.py
crwy/utils/mail.py
crwy/utils/pyppeteer_api.py
crwy/utils/selenium_api.py
crwy/utils/data/RedisHash.py
crwy/utils/data/__init__.py
crwy/utils/extend/__init__.py
crwy/utils/extend/chaojiying.py
crwy/utils/extend/dingding_robot.py
crwy/utils/extend/xunma.py
crwy/utils/extend/yima.py
crwy/utils/filter/RedisSet.py
crwy/utils/filter/RedisSortedSet.py
crwy/utils/filter/__init__.py
crwy/utils/html/__init__.py
crwy/utils/html/font_analysis.py
crwy/utils/html/html_downloader.py
crwy/utils/html/html_parser.py
crwy/utils/no_sql/__init__.py
crwy/utils/no_sql/redis_m.py
crwy/utils/queue/RedisQueue.py
crwy/utils/queue/SsdbQueue.py
crwy/utils/queue/__init__.py
crwy/utils/scrapy_plugs/__init__.py
crwy/utils/scrapy_plugs/dupefilters.py
crwy/utils/scrapy_plugs/middlewares.py
crwy/utils/scrapy_plugs/pipelines.py
crwy/utils/scrapy_plugs/settings.py
crwy/utils/sql/__init__.py
crwy/utils/sql/mysql.py
crwy/utils/sql/pg.py
crwy/utils/sql/sqlalchemy_m.py