Metadata-Version: 1.2
Name: Crwy
Version: 1.6.0
Summary: A Simple Web Crawling and Web Scraping framework
Home-page: https://github.com/wuyue92tree/crwy
Author: wuyue
Author-email: wuyue92tree@163.com
Maintainer: wuyue
Maintainer-email: wuyue92tree@163.com
License: MIT
Platform: UNKNOWN
